{"nm":"C","h":500,"w":500,"meta":{"g":"@lottiefiles/toolkit-js 0.33.2"},"layers":[{"ty":3,"nm":"N","sr":1,"st":0,"op":90,"ip":0,"hasMask":false,"ao":0,"ks":{"a":{"a":0,"k":[50,50,0]},"s":{"a":0,"k":[1000,1000,100]},"sk":{"a":0,"k":0},"p":{"a":0,"k":[250,250,0]},"r":{"a":0,"k":0},"sa":{"a":0,"k":0},"o":{"a":0,"k":0}},"ef":[],"ind":1},{"ty":4,"nm":"G","sr":1,"st":0,"op":90,"ip":0,"hasMask":false,"ao":0,"ks":{"a":{"a":0,"k":[-6.602,4.008,0]},"s":{"a":1,"k":[{"o":{"x":0.333,"y":0},"i":{"x":0.667,"y":1},"s":[100,100,100],"t":0},{"o":{"x":0.333,"y":0},"i":{"x":0.667,"y":1},"s":[110,90,100],"t":5},{"o":{"x":0.333,"y":0},"i":{"x":0.667,"y":1},"s":[90,95,100],"t":10},{"o":{"x":0.333,"y":0},"i":{"x":0.667,"y":1},"s":[110,90,100],"t":15},{"o":{"x":0.333,"y":0},"i":{"x":0.667,"y":1},"s":[90,95,100],"t":20},{"s":[100,100,100],"t":25}]},"sk":{"a":0,"k":0},"p":{"a":0,"k":[42.546,50.19,0]},"r":{"a":0,"k":0},"sa":{"a":0,"k":0},"o":{"a":0,"k":100}},"ef":[],"shapes":[{"ty":"gr","nm":"G","it":[{"ty":"gr","nm":"G","it":[{"ty":"gr","nm":"G","it":[{"ty":"sh","nm":"P","d":1,"ks":{"a":1,"k":[{"o":{"x":0.333,"y":0},"i":{"x":0.667,"y":1},"s":[{"c":true,"i":[[0,-2.252],[1.188,-0.703],[0,0],[0.275,-1.368],[0,1.482],[0,0]],"o":[[0,1.482],[-0.275,-1.368],[0,0],[-1.188,-0.703],[0,-2.252],[0,0]],"v":[[-2.522,0.522],[-4.507,4.008],[-6.607,-0.153],[-8.697,4.008],[-10.682,0.522],[-6.607,-7.99]]}],"t":0},{"o":{"x":0.333,"y":0},"i":{"x":0.667,"y":1},"s":[{"c":true,"i":[[0,-2.252],[1.188,-0.703],[0,0],[0.275,-1.368],[0,1.482],[0,0]],"o":[[0,1.482],[-0.275,-1.368],[0,0],[-1.188,-0.703],[0,-2.252],[0,0]],"v":[[-2.522,0.522],[-4.507,4.008],[-6.607,-0.153],[-8.697,4.008],[-10.682,0.522],[-7.907,-7.99]]}],"t":5},{"o":{"x":0.333,"y":0},"i":{"x":0.667,"y":1},"s":[{"c":true,"i":[[0,-2.252],[1.188,-0.703],[0,0],[0.275,-1.368],[0,1.482],[0,0]],"o":[[0,1.482],[-0.275,-1.368],[0,0],[-1.188,-0.703],[0,-2.252],[0,0]],"v":[[-2.522,0.522],[-4.507,4.008],[-6.607,-0.153],[-8.697,4.008],[-10.682,0.522],[-6.932,-9.149]]}],"t":10},{"o":{"x":0.333,"y":0},"i":{"x":0.667,"y":1},"s":[{"c":true,"i":[[0,-2.252],[1.188,-0.703],[0,0],[0.275,-1.368],[0,1.482],[0,0]],"o":[[0,1.482],[-0.275,-1.368],[0,0],[-1.188,-0.703],[0,-2.252],[0,0]],"v":[[-2.522,0.522],[-4.507,4.008],[-6.607,-0.153],[-8.697,4.008],[-10.682,0.522],[-5.484,-8]]}],"t":15},{"o":{"x":0.333,"y":0},"i":{"x":0.667,"y":1},"s":[{"c":true,"i":[[0,-2.252],[1.188,-0.703],[0,0],[0.275,-1.368],[0,1.482],[0,0]],"o":[[0,1.482],[-0.275,-1.368],[0,0],[-1.188,-0.703],[0,-2.252],[0,0]],"v":[[-2.522,0.522],[-4.507,4.008],[-6.607,-0.153],[-8.697,4.008],[-10.682,0.522],[-6.429,-11.324]]}],"t":20},{"s":[{"c":true,"i":[[0,-2.252],[1.188,-0.703],[0,0],[0.275,-1.368],[0,1.482],[0,0]],"o":[[0,1.482],[-0.275,-1.368],[0,0],[-1.188,-0.703],[0,-2.252],[0,0]],"v":[[-2.522,0.522],[-4.507,4.008],[-6.607,-0.153],[-8.697,4.008],[-10.682,0.522],[-6.607,-7.99]]}],"t":25}]}},{"ty":"st","nm":"S","lc":2,"lj":2,"ml":1,"o":{"a":0,"k":100},"w":{"a":0,"k":1.5},"c":{"a":0,"k":[0.302,0.302,0.302]}},{"ty":"fl","nm":"F","c":{"a":0,"k":[1,0.898,0.486]},"r":1,"o":{"a":0,"k":100}},{"ty":"tr","a":{"a":0,"k":[0,0]},"s":{"a":0,"k":[100,100]},"sk":{"a":0,"k":0},"p":{"a":0,"k":[0,0]},"r":{"a":0,"k":0},"sa":{"a":0,"k":0},"o":{"a":0,"k":100}}]},{"ty":"tr","a":{"a":0,"k":[0,0]},"s":{"a":0,"k":[100,100]},"sk":{"a":0,"k":0},"p":{"a":0,"k":[0,0]},"r":{"a":0,"k":0},"sa":{"a":0,"k":0},"o":{"a":0,"k":100}}]},{"ty":"tr","a":{"a":0,"k":[0,0]},"s":{"a":0,"k":[100,100]},"sk":{"a":0,"k":0},"p":{"a":0,"k":[0,0]},"r":{"a":0,"k":0},"sa":{"a":0,"k":0},"o":{"a":0,"k":100}}]}],"ind":2,"parent":1},{"ty":4,"nm":"P","sr":1,"st":0,"op":90,"ip":0,"hasMask":false,"ao":0,"ks":{"a":{"a":0,"k":[295.517,250,0]},"s":{"a":0,"k":[10,10,100]},"sk":{"a":0,"k":0},"p":{"a":0,"k":[54.552,50,0]},"r":{"a":0,"k":0},"sa":{"a":0,"k":0},"o":{"a":0,"k":100}},"ef":[],"shapes":[{"ty":"gr","nm":"P","it":[{"ty":"gr","nm":"G","it":[{"ty":"gr","nm":"G","it":[{"ty":"gr","nm":"G","it":[{"ty":"sh","nm":"P","d":1,"ks":{"a":0,"k":{"c":false,"i":[[0,0],[0,0]],"o":[[0,0],[0,0]],"v":[[12.386,2.828],[14.023,2.828]]}}},{"ty":"st","nm":"S","lc":2,"lj":2,"ml":1,"o":{"a":0,"k":100},"w":{"a":0,"k":1.5},"c":{"a":0,"k":[0.302,0.302,0.302]}},{"ty":"fl","nm":"F","c":{"a":0,"k":[1,0.333,0.337]},"r":1,"o":{"a":0,"k":100}},{"ty":"tr","a":{"a":0,"k":[0,0]},"s":{"a":0,"k":[100,100]},"sk":{"a":0,"k":0},"p":{"a":0,"k":[0,0]},"r":{"a":0,"k":0},"sa":{"a":0,"k":0},"o":{"a":0,"k":100}}]},{"ty":"tr","a":{"a":0,"k":[0,0]},"s":{"a":0,"k":[100,100]},"sk":{"a":0,"k":0},"p":{"a":0,"k":[0,0]},"r":{"a":0,"k":0},"sa":{"a":0,"k":0},"o":{"a":0,"k":100}}]},{"ty":"tr","a":{"a":0,"k":[0,0]},"s":{"a":0,"k":[100,100]},"sk":{"a":0,"k":0},"p":{"a":0,"k":[0,0]},"r":{"a":0,"k":0},"sa":{"a":0,"k":0},"o":{"a":0,"k":100}}]},{"ty":"tm","nm":"T","e":{"a":1,"k":[{"o":{"x":0.333,"y":0},"i":{"x":0.667,"y":1},"s":[0],"t":14},{"s":[100],"t":29}]},"o":{"a":0,"k":0},"s":{"a":0,"k":0},"m":1},{"ty":"tr","a":{"a":0,"k":[13.205,2.828]},"s":{"a":0,"k":[1000,1000]},"sk":{"a":0,"k":0},"p":{"a":0,"k":[373.526,240.102]},"r":{"a":0,"k":0},"sa":{"a":0,"k":0},"o":{"a":0,"k":100}}]},{"ty":"gr","nm":"P","it":[{"ty":"gr","nm":"G","it":[{"ty":"gr","nm":"G","it":[{"ty":"gr","nm":"G","it":[{"ty":"sh","nm":"P","d":1,"ks":{"a":0,"k":{"c":false,"i":[[0,0],[0,0]],"o":[[0,0],[0,0]],"v":[[12.386,-1.553],[14.023,-1.553]]}}},{"ty":"st","nm":"S","lc":2,"lj":2,"ml":1,"o":{"a":0,"k":100},"w":{"a":0,"k":1.5},"c":{"a":0,"k":[0.302,0.302,0.302]}},{"ty":"fl","nm":"F","c":{"a":0,"k":[1,0.333,0.337]},"r":1,"o":{"a":0,"k":100}},{"ty":"tr","a":{"a":0,"k":[0,0]},"s":{"a":0,"k":[100,100]},"sk":{"a":0,"k":0},"p":{"a":0,"k":[0,0]},"r":{"a":0,"k":0},"sa":{"a":0,"k":0},"o":{"a":0,"k":100}}]},{"ty":"tr","a":{"a":0,"k":[0,0]},"s":{"a":0,"k":[100,100]},"sk":{"a":0,"k":0},"p":{"a":0,"k":[0,0]},"r":{"a":0,"k":0},"sa":{"a":0,"k":0},"o":{"a":0,"k":100}}]},{"ty":"tr","a":{"a":0,"k":[0,0]},"s":{"a":0,"k":[100,100]},"sk":{"a":0,"k":0},"p":{"a":0,"k":[0,0]},"r":{"a":0,"k":0},"sa":{"a":0,"k":0},"o":{"a":0,"k":100}}]},{"ty":"tm","nm":"T","e":{"a":1,"k":[{"o":{"x":0.333,"y":0},"i":{"x":0.667,"y":1},"s":[0],"t":7},{"s":[100],"t":22}]},"o":{"a":0,"k":0},"s":{"a":0,"k":0},"m":1},{"ty":"tr","a":{"a":0,"k":[13.205,-1.553]},"s":{"a":0,"k":[1000,1000]},"sk":{"a":0,"k":0},"p":{"a":0,"k":[373.526,196.287]},"r":{"a":0,"k":0},"sa":{"a":0,"k":0},"o":{"a":0,"k":100}}]},{"ty":"gr","nm":"P","it":[{"ty":"gr","nm":"G","it":[{"ty":"gr","nm":"G","it":[{"ty":"gr","nm":"G","it":[{"ty":"sh","nm":"P","d":1,"ks":{"a":0,"k":{"c":false,"i":[[0,0],[0,0]],"o":[[0,0],[0,0]],"v":[[12.386,-5.935],[14.023,-5.935]]}}},{"ty":"st","nm":"S","lc":2,"lj":2,"ml":1,"o":{"a":0,"k":100},"w":{"a":0,"k":1.5},"c":{"a":0,"k":[0.302,0.302,0.302]}},{"ty":"fl","nm":"F","c":{"a":0,"k":[1,0.333,0.337]},"r":1,"o":{"a":0,"k":100}},{"ty":"tr","a":{"a":0,"k":[0,0]},"s":{"a":0,"k":[100,100]},"sk":{"a":0,"k":0},"p":{"a":0,"k":[0,0]},"r":{"a":0,"k":0},"sa":{"a":0,"k":0},"o":{"a":0,"k":100}}]},{"ty":"tr","a":{"a":0,"k":[0,0]},"s":{"a":0,"k":[100,100]},"sk":{"a":0,"k":0},"p":{"a":0,"k":[0,0]},"r":{"a":0,"k":0},"sa":{"a":0,"k":0},"o":{"a":0,"k":100}}]},{"ty":"tr","a":{"a":0,"k":[0,0]},"s":{"a":0,"k":[100,100]},"sk":{"a":0,"k":0},"p":{"a":0,"k":[0,0]},"r":{"a":0,"k":0},"sa":{"a":0,"k":0},"o":{"a":0,"k":100}}]},{"ty":"tm","nm":"T","e":{"a":1,"k":[{"o":{"x":0.333,"y":0},"i":{"x":0.667,"y":1},"s":[0],"t":0},{"s":[100],"t":15}]},"o":{"a":0,"k":0},"s":{"a":0,"k":0},"m":1},{"ty":"tr","a":{"a":0,"k":[13.205,-5.935]},"s":{"a":0,"k":[1000,1000]},"sk":{"a":0,"k":0},"p":{"a":0,"k":[373.526,152.472]},"r":{"a":0,"k":0},"sa":{"a":0,"k":0},"o":{"a":0,"k":100}}]},{"ty":"gr","nm":"I","it":[{"ty":"gr","nm":"G","it":[{"ty":"gr","nm":"G","it":[{"ty":"gr","nm":"G","it":[{"ty":"st","nm":"S","lc":2,"lj":2,"ml":1,"o":{"a":0,"k":100},"w":{"a":0,"k":1.5},"c":{"a":0,"k":[0.302,0.302,0.302]}},{"ty":"fl","nm":"F","c":{"a":0,"k":[1,0.333,0.337]},"r":1,"o":{"a":0,"k":100}},{"ty":"tr","a":{"a":0,"k":[0,0]},"s":{"a":0,"k":[100,100]},"sk":{"a":0,"k":0},"p":{"a":0,"k":[0,0]},"r":{"a":0,"k":0},"sa":{"a":0,"k":0},"o":{"a":0,"k":100}}]},{"ty":"gr","nm":"G","it":[{"ty":"st","nm":"S","lc":2,"lj":2,"ml":1,"o":{"a":0,"k":100},"w":{"a":0,"k":1.5},"c":{"a":0,"k":[0.302,0.302,0.302]}},{"ty":"fl","nm":"F","c":{"a":0,"k":[1,0.333,0.337]},"r":1,"o":{"a":0,"k":100}},{"ty":"tr","a":{"a":0,"k":[0,0]},"s":{"a":0,"k":[100,100]},"sk":{"a":0,"k":0},"p":{"a":0,"k":[0,0]},"r":{"a":0,"k":0},"sa":{"a":0,"k":0},"o":{"a":0,"k":100}}]},{"ty":"gr","nm":"G","it":[{"ty":"st","nm":"S","lc":2,"lj":2,"ml":1,"o":{"a":0,"k":100},"w":{"a":0,"k":1.5},"c":{"a":0,"k":[0.302,0.302,0.302]}},{"ty":"fl","nm":"F","c":{"a":0,"k":[1,0.333,0.337]},"r":1,"o":{"a":0,"k":100}},{"ty":"tr","a":{"a":0,"k":[0,0]},"s":{"a":0,"k":[100,100]},"sk":{"a":0,"k":0},"p":{"a":0,"k":[0,0]},"r":{"a":0,"k":0},"sa":{"a":0,"k":0},"o":{"a":0,"k":100}}]},{"ty":"tr","a":{"a":0,"k":[0,0]},"s":{"a":0,"k":[100,100]},"sk":{"a":0,"k":0},"p":{"a":0,"k":[0,0]},"r":{"a":0,"k":0},"sa":{"a":0,"k":0},"o":{"a":0,"k":100}}]},{"ty":"gr","nm":"G","it":[{"ty":"gr","nm":"G","it":[{"ty":"gr","nm":"G","it":[{"ty":"sh","nm":"P","d":1,"ks":{"a":1,"k":[{"o":{"x":0.333,"y":0},"i":{"x":0.667,"y":1},"s":[{"c":false,"i":[[0,0],[0,0]],"o":[[0,0],[0,0]],"v":[[5.404,9.169],[5.405,5.783]]}],"t":0},{"s":[{"c":false,"i":[[0,0],[0,0]],"o":[[0,0],[0,0]],"v":[[5.404,9.169],[5.404,-7.117]]}],"t":25}]}},{"ty":"st","nm":"S","lc":2,"lj":2,"ml":1,"o":{"a":0,"k":100},"w":{"a":0,"k":1.5},"c":{"a":0,"k":[0.302,0.302,0.302]}},{"ty":"fl","nm":"F","c":{"a":0,"k":[0.937,0.937,0.937]},"r":1,"o":{"a":0,"k":100}},{"ty":"tr","a":{"a":0,"k":[0,0]},"s":{"a":0,"k":[100,100]},"sk":{"a":0,"k":0},"p":{"a":0,"k":[0,0]},"r":{"a":0,"k":0},"sa":{"a":0,"k":0},"o":{"a":0,"k":100}}]},{"ty":"tr","a":{"a":0,"k":[0,0]},"s":{"a":0,"k":[100,100]},"sk":{"a":0,"k":0},"p":{"a":0,"k":[0,0]},"r":{"a":0,"k":0},"sa":{"a":0,"k":0},"o":{"a":0,"k":100}}]},{"ty":"gr","nm":"G","it":[{"ty":"sh","nm":"P","d":1,"ks":{"a":0,"k":{"c":true,"i":[[0,-1.58],[1.58,0],[0,1.58],[-1.58,0]],"o":[[0,1.58],[-1.58,0],[0,-1.58],[1.58,0]],"v":[[8.264,12.029],[5.404,14.89],[2.543,12.029],[5.404,9.169]]}}},{"ty":"st","nm":"S","lc":2,"lj":2,"ml":1,"o":{"a":0,"k":100},"w":{"a":0,"k":1.5},"c":{"a":0,"k":[0.302,0.302,0.302]}},{"ty":"fl","nm":"F","c":{"a":0,"k":[1,0.333,0.337]},"r":1,"o":{"a":0,"k":100}},{"ty":"tr","a":{"a":0,"k":[0,0]},"s":{"a":0,"k":[100,100]},"sk":{"a":0,"k":0},"p":{"a":0,"k":[0,0]},"r":{"a":0,"k":0},"sa":{"a":0,"k":0},"o":{"a":0,"k":100}}]},{"ty":"gr","nm":"G","it":[{"ty":"sh","nm":"P","d":1,"ks":{"a":0,"k":{"c":true,"i":[[0,-2.346],[3.857,0],[0,3.857],[-1.767,1.264],[0,0],[-0.732,0.732],[-1.121,0],[0,-2.242],[0,0]],"o":[[0,3.857],[-3.857,0],[0,-2.346],[0,0],[0,-1.121],[0.731,-0.732],[2.242,0],[0,0],[1.767,1.264]],"v":[[12.386,12.026],[5.404,19.018],[-1.579,12.026],[1.347,6.345],[1.347,-7.326],[2.535,-10.195],[5.404,-11.382],[9.46,-7.326],[9.46,6.345]]}}},{"ty":"st","nm":"S","lc":2,"lj":2,"ml":1,"o":{"a":0,"k":100},"w":{"a":0,"k":1.5},"c":{"a":0,"k":[0.302,0.302,0.302]}},{"ty":"fl","nm":"F","c":{"a":0,"k":[0.937,0.937,0.937]},"r":1,"o":{"a":0,"k":100}},{"ty":"tr","a":{"a":0,"k":[0,0]},"s":{"a":0,"k":[100,100]},"sk":{"a":0,"k":0},"p":{"a":0,"k":[0,0]},"r":{"a":0,"k":0},"sa":{"a":0,"k":0},"o":{"a":0,"k":100}}]},{"ty":"tr","a":{"a":0,"k":[0,0]},"s":{"a":0,"k":[100,100]},"sk":{"a":0,"k":0},"p":{"a":0,"k":[0,0]},"r":{"a":0,"k":0},"sa":{"a":0,"k":0},"o":{"a":0,"k":100}}]},{"ty":"tr","a":{"a":0,"k":[0,0]},"s":{"a":0,"k":[100,100]},"sk":{"a":0,"k":0},"p":{"a":0,"k":[0,0]},"r":{"a":0,"k":0},"sa":{"a":0,"k":0},"o":{"a":0,"k":100}}]},{"ty":"tr","a":{"a":0,"k":[1.671,3.818]},"s":{"a":0,"k":[1000,1000]},"sk":{"a":0,"k":0},"p":{"a":0,"k":[258.185,250]},"r":{"a":0,"k":0},"sa":{"a":0,"k":0},"o":{"a":0,"k":100}}]}],"ind":3,"parent":1}],"v":"5.10.0","fr":29,"op":40,"ip":0,"assets":[]}